moonfish/__init__.py
moonfish/config.py
moonfish/helper.py
moonfish/lib.py
moonfish/main.py
moonfish/move_ordering.py
moonfish/psqt.py
moonfish/py.typed
moonfish/engines/alpha_beta.py
moonfish/engines/base_engine.py
moonfish/engines/l1p_alpha_beta.py
moonfish/engines/l2p_alpha_beta.py
moonfish/engines/lazy_smp.py
moonfish/engines/random.py
moonfish/mode/api.py
moonfish/mode/uci.py
moonfish-0.0.1.dist-info/licenses/LICENSE
moonfish-0.0.1.dist-info/METADATA
moonfish-0.0.1.dist-info/WHEEL
moonfish-0.0.1.dist-info/entry_points.txt
moonfish-0.0.1.dist-info/top_level.txt
moonfish-0.0.1.dist-info/RECORD
