Metadata-Version: 2.4
Name: moonfish
Version: 0.0.1
Summary: Moonfish is a didactic Python chess engine showcasing parallel search algorithms and modern chess programming techniques.
Author-email: Lucca Bertoncini <luccabazzo@gmail.com>
License: MIT License
Project-URL: Homepage, https://github.com/luccabb/moonfish
Project-URL: Issues, https://github.com/luccabb/moonfish/issues
Requires-Python: >=3.10
License-File: LICENSE
Requires-Dist: chess
Requires-Dist: click
Requires-Dist: Flask
Requires-Dist: Flask-Cors
Requires-Dist: parameterized
Requires-Dist: pyinstaller
Requires-Dist: mypy
Requires-Dist: flake8
Requires-Dist: black
Requires-Dist: isort
Requires-Dist: ufmt
Requires-Dist: types-flask-cors>=6.0.0.20250520
Dynamic: license-file
